ssssg/__init__.py
ssssg/__version__.py
ssssg/create_site.py
ssssg/logger.py
ssssg/site_creator.py
ssssg/filters/__init__.py
ssssg/filters/to_markdown.py
ssssg-3.1.1.dist-info/LICENSE
ssssg-3.1.1.dist-info/METADATA
ssssg-3.1.1.dist-info/WHEEL
ssssg-3.1.1.dist-info/entry_points.txt
ssssg-3.1.1.dist-info/top_level.txt
ssssg-3.1.1.dist-info/RECORD
