Metadata-Version: 2.1
Name: ssssg
Version: 3.1.1
Summary: Stupidly Simple Static Site Generator
Author-email: Kyle Graves <octesian@protonmail.com>
License: GNU GENERAL PUBLIC LICENSE
Project-URL: Issue Tracker, https://gitlab.com/octesian/ssssg/-/issues
Project-URL: Git, https://gitlab.com/octesian/ssssg
Classifier: Programming Language :: Python :: 3
Classifier: License :: OSI Approved :: GNU General Public License v3 or later (GPLv3+)
Classifier: Operating System :: OS Independent
License-File: LICENSE
Requires-Dist: jinja2 (~=3.0.2)
Requires-Dist: libsass (~=0.21.0)
Requires-Dist: markdown (~=3.4.1)
Provides-Extra: deploy
Requires-Dist: python-semantic-release (~=7.31.4) ; extra == 'deploy'
Provides-Extra: docs
Requires-Dist: sphinx (~=4.4.0) ; extra == 'docs'
Requires-Dist: sphinx-rtd-theme (~=1.0.0) ; extra == 'docs'
Requires-Dist: sphinx-rtd-dark-mode ; extra == 'docs'
Requires-Dist: sphinx-autoapi ; extra == 'docs'
Requires-Dist: sphinx-pyproject ; extra == 'docs'
Requires-Dist: Pygments ; extra == 'docs'
Provides-Extra: test
Requires-Dist: pytest (~=7.0.1) ; extra == 'test'
Requires-Dist: pytest-cov (~=3.0.0) ; extra == 'test'
Requires-Dist: setuptools-scm[toml] (~=7.0.5) ; extra == 'test'
Requires-Dist: black (~=22.6.0) ; extra == 'test'
